tofupilot_py/__init__.py
tofupilot_py/_hooks/__init__.py
tofupilot_py/_hooks/sdkhooks.py
tofupilot_py/_hooks/types.py
tofupilot_py/_version.py
tofupilot_py/basesdk.py
tofupilot_py/errors/__init__.py
tofupilot_py/errors/apierror.py
tofupilot_py/errors/error_bad_gateway.py
tofupilot_py/errors/error_bad_request.py
tofupilot_py/errors/error_conflict.py
tofupilot_py/errors/error_forbidden.py
tofupilot_py/errors/error_internal_server_error.py
tofupilot_py/errors/error_not_found.py
tofupilot_py/errors/error_unauthorized.py
tofupilot_py/httpclient.py
tofupilot_py/imports.py
tofupilot_py/models/__init__.py
tofupilot_py/models/error_bad_gateway.py
tofupilot_py/models/error_bad_request.py
tofupilot_py/models/error_conflict.py
tofupilot_py/models/error_forbidden.py
tofupilot_py/models/error_internal_server_error.py
tofupilot_py/models/error_not_found.py
tofupilot_py/models/error_unauthorized.py
tofupilot_py/models/run_createfromfileop.py
tofupilot_py/models/run_createop.py
tofupilot_py/models/run_deletesingleop.py
tofupilot_py/models/run_getrunsbyserialnumberop.py
tofupilot_py/models/security.py
tofupilot_py/models/streaming_getstreamingtokenop.py
tofupilot_py/models/unit_deleteop.py
tofupilot_py/models/unit_updateunitparentop.py
tofupilot_py/models/upload_initializeop.py
tofupilot_py/models/upload_syncuploadop.py
tofupilot_py/py.typed
tofupilot_py/runs.py
tofupilot_py/sdk.py
tofupilot_py/sdkconfiguration.py
tofupilot_py/streaming.py
tofupilot_py/types/__init__.py
tofupilot_py/types/basemodel.py
tofupilot_py/units_sdk.py
tofupilot_py/uploads.py
tofupilot_py/utils/__init__.py
tofupilot_py/utils/annotations.py
tofupilot_py/utils/datetimes.py
tofupilot_py/utils/enums.py
tofupilot_py/utils/eventstreaming.py
tofupilot_py/utils/forms.py
tofupilot_py/utils/headers.py
tofupilot_py/utils/logger.py
tofupilot_py/utils/metadata.py
tofupilot_py/utils/queryparams.py
tofupilot_py/utils/requestbodies.py
tofupilot_py/utils/retries.py
tofupilot_py/utils/security.py
tofupilot_py-0.1.0.dist-info/METADATA
tofupilot_py-0.1.0.dist-info/WHEEL
tofupilot_py-0.1.0.dist-info/RECORD
